python_server_MPZinke/__init__.py
python_server_MPZinke-0.0.1.dist-info/LICENSE
python_server_MPZinke-0.0.1.dist-info/METADATA
python_server_MPZinke-0.0.1.dist-info/WHEEL
python_server_MPZinke-0.0.1.dist-info/top_level.txt
python_server_MPZinke-0.0.1.dist-info/RECORD
