Metadata-Version: 2.1
Name: python_server_MPZinke
Version: 0.0.1
Summary: A Flask server class for simple routing by HTTP method.
Author: Mathew Zinke
Project-URL: Homepage, https://github.com/MPZinke/PythonServer
Project-URL: Bug Tracker, https://github.com/MPZinke/PythonServer/issues
Classifier: Programming Language :: Python :: 3
Classifier: License :: OSI Approved :: GNU General Public License v3 (GPLv3)
Classifier: Operating System :: OS Independent
Requires-Python: >=3.11
License-File: LICENSE
